{
  "kawasaki": { "lat": 35.5313, "lng": 139.6969 },
  "shitte": { "lat": 35.5308, "lng": 139.6843 },
  "yako": { "lat": 35.5393, "lng": 139.6804 },
  "kashimada": { "lat": 35.5515, "lng": 139.6749 },
  "hirama": { "lat": 35.5605, "lng": 139.6710 },
  "mukaigawara": { "lat": 35.5721, "lng": 139.6673 },
  "musashikosugi": { "lat": 35.5765, "lng": 139.6598 },
  "musashinakahara": { "lat": 35.5806, "lng": 139.6421 },
  "musashishinjo": { "lat": 35.5873, "lng": 139.6295 },
  "musashimizonokuchi": { "lat": 35.5987, "lng": 139.6115 },
  "tsudayama": { "lat": 35.6037, "lng": 139.6007 },
  "kuji": { "lat": 35.6101, "lng": 139.5929 },
  "shukugawara": { "lat": 35.6154, "lng": 139.5794 },
  "noborito": { "lat": 35.6207, "lng": 139.5703 },
  "nakanoshima": { "lat": 35.6300, "lng": 139.5510 },
  "inadazutsumi": { "lat": 35.6333, "lng": 139.5361 },
  "yanokuchi": { "lat": 35.6417, "lng": 139.5203 },
  "inaginaganuma": { "lat": 35.6444, "lng": 139.5020 },
  "minamitama": { "lat": 35.6492, "lng": 139.4899 },
  "fuchuhommachi": { "lat": 35.6658, "lng": 139.4771 },
  "bubaigawara": { "lat": 35.6684, "lng": 139.4690 },
  "nishifu": { "lat": 35.6709, "lng": 139.4573 },
  "yaho": { "lat": 35.6812, "lng": 139.4471 },
  "yagawa": { "lat": 35.6850, "lng": 139.4314 },
  "nishikunitachi": { "lat": 35.6938, "lng": 139.4239 },
  "tachikawa": { "lat": 35.6978, "lng": 139.4137 },
}
